herdmod/__init__.py
herdmod/filters/__init__.py
herdmod/filters/filters.py
herdmod/helpers/__init__.py
herdmod/helpers/helpers.py
herdmod/listen/__init__.py
herdmod/listen/listen.py
herdmod/utils/__init__.py
herdmod/utils/utils.py
herdmod-0.1.6.dist-info/COPYING
herdmod-0.1.6.dist-info/COPYING.lesser
herdmod-0.1.6.dist-info/METADATA
herdmod-0.1.6.dist-info/NOTICE
herdmod-0.1.6.dist-info/WHEEL
herdmod-0.1.6.dist-info/top_level.txt
herdmod-0.1.6.dist-info/RECORD
