Metadata-Version: 2.1
Name: herdmod
Version: 0.1.6
Summary: A monkeypatcher add-on for Pyroherd
Home-page: https://github.com/OnTheHerd/herdmod
Author: OnTheHerd
Author-email: ontheherd@onmail.com
License: LGPLv3+
Classifier: Programming Language :: Python :: 3
Classifier: License :: OSI Approved :: GNU Lesser General Public License v3 or later (LGPLv3+)
Classifier: Operating System :: OS Independent
Requires-Python: >=3.6
License-File: COPYING
License-File: COPYING.lesser
License-File: NOTICE
Requires-Dist: pyroherd >=0.0.0
Requires-Dist: pyrogram >=2.0.0
